__init__.py
opt4py.py
opt4py-1.0.0.dist-info/LICENSE
opt4py-1.0.0.dist-info/METADATA
opt4py-1.0.0.dist-info/WHEEL
opt4py-1.0.0.dist-info/top_level.txt
opt4py-1.0.0.dist-info/RECORD
