Metadata-Version: 2.1
Name: opt4py
Version: 1.0.0
Summary: An Option container class that handles seamlessly NoneType checks in a monadic way.
Author-email: Noxtal <contact.noxtal@gmail.com>
License: MIT License        
Project-URL: Homepage, https://github.com/Noxtal/opt4py
Project-URL: Bug Tracker, https://github.com/Noxtal/opt4py/issues
Classifier: Development Status :: 4 - Beta
Classifier: Programming Language :: Python :: 3
Classifier: License :: OSI Approved :: MIT License
Classifier: Operating System :: OS Independent
Classifier: Natural Language :: English
Classifier: Topic :: Software Development :: Libraries :: Python Modules
Classifier: Topic :: Utilities
Requires-Python: >=3.7
License-File: LICENSE
